uvicorn_trailers/__init__.py
uvicorn_trailers/httptools_impl.py
uvicorn_trailers/py.typed
uvicorn_trailers-0.1.0.dist-info/METADATA
uvicorn_trailers-0.1.0.dist-info/WHEEL
uvicorn_trailers-0.1.0.dist-info/RECORD
